agent_contracts/__init__.py
agent_contracts/cli.py
agent_contracts/contract_diff.py
agent_contracts/contracts.py
agent_contracts/errors.py
agent_contracts/graph_builder.py
agent_contracts/node.py
agent_contracts/py.typed
agent_contracts/registry.py
agent_contracts/router.py
agent_contracts/routing.py
agent_contracts/state.py
agent_contracts/state_accessors.py
agent_contracts/subgraph.py
agent_contracts/supervisor.py
agent_contracts/validator.py
agent_contracts/visualizer.py
agent_contracts/config/__init__.py
agent_contracts/config/defaults.yaml
agent_contracts/config/loader.py
agent_contracts/config/questions.py
agent_contracts/config/questions_example.yaml
agent_contracts/config/schema.py
agent_contracts/runtime/__init__.py
agent_contracts/runtime/context.py
agent_contracts/runtime/executor.py
agent_contracts/runtime/hierarchy.py
agent_contracts/runtime/hooks.py
agent_contracts/runtime/session.py
agent_contracts/runtime/state_ops.py
agent_contracts/runtime/streaming.py
agent_contracts/store/__init__.py
agent_contracts/store/base.py
agent_contracts/store/memory.py
agent_contracts/utils/__init__.py
agent_contracts/utils/json.py
agent_contracts/utils/logging.py
agent_contracts/utils/sanitize_context.py
agent_contracts-0.6.0.dist-info/METADATA
agent_contracts-0.6.0.dist-info/WHEEL
agent_contracts-0.6.0.dist-info/entry_points.txt
agent_contracts-0.6.0.dist-info/licenses/LICENSE
agent_contracts-0.6.0.dist-info/RECORD
