Metadata-Version: 2.4
Name: agent-contracts
Version: 0.6.0
Summary: Modular node architecture for LangGraph agents
Project-URL: Homepage, https://github.com/yatarousan0227/agent-contracts
Project-URL: Repository, https://github.com/yatarousan0227/agent-contracts
Author: Shinya Iwasaki
License: MPL-2.0
License-File: LICENSE
Keywords: agents,contracts,langgraph,modular
Classifier: Development Status :: 4 - Beta
Classifier: Intended Audience :: Developers
Classifier: License :: OSI Approved :: Mozilla Public License 2.0 (MPL 2.0)
Classifier: Programming Language :: Python :: 3.11
Classifier: Programming Language :: Python :: 3.12
Requires-Python: >=3.11
Requires-Dist: langchain-core>=0.3.0
Requires-Dist: langgraph>=0.2.0
Requires-Dist: pydantic>=2.0.0
Requires-Dist: pyyaml>=6.0.0
Provides-Extra: dev
Requires-Dist: pytest-asyncio>=0.24.0; extra == 'dev'
Requires-Dist: pytest-cov>=5.0.0; extra == 'dev'
Requires-Dist: pytest>=8.0.0; extra == 'dev'
Requires-Dist: ruff>=0.1.0; extra == 'dev'
Provides-Extra: structlog
Requires-Dist: structlog>=24.0.0; extra == 'structlog'
